dokr_pkg/__init__.py
dokr_pkg/anonymous_matlab.py
dokr_pkg/try1.py
dokr_pkg/vit2.py
dokr_pkg/vit3.py
dokr_pkg/pyperclip/__init__.py
dokr_pkg/pyperclip/__main__.py
vit3.py-0.1.data/scripts/abc_matlab.py
vit3.py-0.1.data/scripts/anonymous_matlab.py
vit3.py-0.1.data/scripts/try1.py
vit3.py-0.1.data/scripts/vit1.py
vit3.py-0.1.data/scripts/vit2.py
vit3.py-0.1.data/scripts/vit3.py
vit3.py-0.1.dist-info/METADATA
vit3.py-0.1.dist-info/WHEEL
vit3.py-0.1.dist-info/top_level.txt
vit3.py-0.1.dist-info/RECORD
